{
  "title": "TIPSY environment description",
  "type": "object",
  "properties": {
    "sut": {
      "type": "object",
      "properties": {
	"type": {
	  "type": "string",
	  "enum": ["ovs", "bess", "ofdpa", "t4p4s"],
	  "default": "ovs"
	},
	"hostname": {
	  "type": "string",
	  "default": "sut.local",
	  "description": "Hostname that can be used to ssh into SUT without a password as 'ssh hostname'.  Edit ~/.ssh/config for more complicated scenarios.  See man page: ssh_config (5)"
	},
	"tipsy-dir": {
	  "type": "string",
	  "default": "/opt/tipsy",
	  "description": "A directory on SUT in which TIPSY is installed"
	},
	"bess-dir": {
	  "type": "string",
	  "default": "/opt/bess",
	  "description": "A directory on SUT in which bess is installed"
	},
	"uplink-port": {
	  "type": "string",
	  "default": "0000:0b:00.0",
	  "description": "Port name ('eth1') or pci addr for DPDK ('0000:0b:00.0') or DPDK port number (in case of moongen, e.g., '0') [TODO: we could calculate this from the pci_addr]"
	},
	"downlink-port": {
	  "type": "string",
	  "default": "0000:0b:00.1",
	  "description": "Port name ('eth1') or pci addr for DPDK ('0000:0b:00.0')  or DPDK port number (in case of moongen, e.g., '0') [TODO: we could calculate this from the pci_addr]"
	},
	"setup-script": {
	  "type": "string",
	  "default": "",
	  "description": "Absolute path of the custom SUT setup script"
	},
	"teardown-script": {
	  "type": "string",
	  "default": "",
	  "description": "Absolute path of the custom SUT teardown script"
	}
      },
      "default": {}
    },
    "tester": {
      "type": "object",
      "properties": {
	"type": {
	  "type": "string",
	  "enum": ["moongen"],
	  "default": "moongen"
	},
	"test-time": {
	  "$ref": "definitions.json#/non-negative-integer",
	  "description": "length of the measurement [s]",
	  "default": 30
	},
	"uplink-port": {
	  "type": "string",
	  "default": "0000:0c:00.1",
	  "description": "Port name ('eth1') or pci addr for DPDK ('0000:0b:00.0') or DPDK port number (in case of moongen, e.g., '0') [TODO: we could calculate this from the pci_addr]"
	},
	"downlink-port": {
	  "type": "string",
	  "default": "0000:0c:00.0",
	  "description": "Port name ('eth1') or pci addr for DPDK ('0000:0b:00.0')  or DPDK port number (in case of moongen, e.g., '0') [TODO: we could calculate this from the pci_addr]"
	},
	"moongen-cmd": {
	  "type": "string",
	  "default": "/opt/MoonGen/build/MoonGen",
	  "description": "Absolute path of the MoonGen executable"
	},
	"setup-script": {
	  "type": "string",
	  "default": "",
	  "description": "Absolute path of the custom Tester setup script"
	},
	"teardown-script": {
	  "type": "string",
	  "default": "",
	  "description": "Absolute path of the custom Tester teardown script"
	}
      },
      "default": {}
    }
  },
  "required": ["sut", "tester"],
  "additionalProperties": false
}
